kenat/__init__.py
kenat/bahire_hasab.py
kenat/constants.py
kenat/conversions.py
kenat/day_arithmetic.py
kenat/exceptions.py
kenat/formatting.py
kenat/geez_converter.py
kenat/holidays.py
kenat/kenat.py
kenat/month_grid.py
kenat/time.py
kenat/utils.py
kenat-1.0.4.dist-info/licenses/LICENSE
kenat-1.0.4.dist-info/METADATA
kenat-1.0.4.dist-info/WHEEL
kenat-1.0.4.dist-info/top_level.txt
kenat-1.0.4.dist-info/RECORD
