Metadata-Version: 2.4
Name: kenat
Version: 1.0.4
Summary: A comprehensive Python library for the Ethiopian calendar, handling conversions, holidays (Bahire Hasab), and date arithmetic.
Author-email: Melaku Demeke <melaku.demeke789@gmail.com>
License: MIT
Project-URL: Homepage, https://www.kenat.systems/
Project-URL: Bug Tracker, https://github.com/MelakuDemeke/kenat/issues
Keywords: ethiopian,calendar,kenat,ethiopia,bahire hasab,date conversion,amharic
Classifier: Development Status :: 5 - Production/Stable
Classifier: Programming Language :: Python :: 3
Classifier: License :: OSI Approved :: MIT License
Classifier: Operating System :: OS Independent
Classifier: Intended Audience :: Developers
Classifier: Topic :: Software Development :: Libraries :: Python Modules
Classifier: Topic :: Utilities
Requires-Python: >=3.8
License-File: LICENSE
Provides-Extra: test
Requires-Dist: pytest; extra == "test"
Requires-Dist: pytest-mock; extra == "test"
Dynamic: license-file
